README
setup.py
test/test_bag.py
test/test_binary_tiddler.py
test/test_gamut.py
test/test_initialization.py
test/test_listing.py
test/test_recipe.py
test/test_tiddler.py
test/test_user.py
test/test_web.py
tiddlywebplugins/__init__.py
tiddlywebplugins.gitstore.egg-info/PKG-INFO
tiddlywebplugins.gitstore.egg-info/SOURCES.txt
tiddlywebplugins.gitstore.egg-info/dependency_links.txt
tiddlywebplugins.gitstore.egg-info/namespace_packages.txt
tiddlywebplugins.gitstore.egg-info/not-zip-safe
tiddlywebplugins.gitstore.egg-info/requires.txt
tiddlywebplugins.gitstore.egg-info/top_level.txt
tiddlywebplugins/gitstore/__init__.py