Metadata-Version: 1.0
Name: tiddlywebplugins.gitstore
Version: 0.6.3
Summary: TiddlyWeb store implementation using Git
Home-page: https://github.com/FND/tiddlywebplugins.gitstore
Author: FND
Author-email: UNKNOWN
License: BSD
Platform: Posix; MacOS X; Windows
